encap_attack/__init__.py
encap_attack/tool.py
encap_attack/utils/__init__.py
encap_attack/utils/encapsulation_models.py
encap_attack/utils/util_models.py
encap_attack/utils/utils.py
encap_attack-1.0.0.dist-info/LICENSE
encap_attack-1.0.0.dist-info/METADATA
encap_attack-1.0.0.dist-info/WHEEL
encap_attack-1.0.0.dist-info/entry_points.txt
encap_attack-1.0.0.dist-info/top_level.txt
encap_attack-1.0.0.dist-info/RECORD
