Metadata-Version: 2.1
Name: encap-attack
Version: 1.0.0
Summary: Network sniffing and attacks using IP-in-IP and VXLAN
Author-email: Matthew Grove <me@mgrove.uk>, Matthew Grove <matthew.grove@withsecure.com>
License: GNU GENERAL PUBLIC LICENSE
Project-URL: Homepage, https://github.com/WithSecureLabs/encap-attack
Project-URL: Repository, https://github.com/WithSecureLabs/encap-attack
Classifier: Programming Language :: Python :: 3.8
Classifier: Operating System :: OS Independent
Requires-Python: >=3.7
License-File: LICENSE
Requires-Dist: cffi
Requires-Dist: click
Requires-Dist: cryptography
Requires-Dist: getmac
Requires-Dist: ipaddress
Requires-Dist: packaging
Requires-Dist: pycparser
Requires-Dist: pyOpenSSL
Requires-Dist: pyproject-hooks
Requires-Dist: scapy
